LICENSE
MANIFEST.in
README.md
setup.py
alurinium/__init__.py
alurinium/image/__init__.py
alurinium/image/base.py
alurinium/image/color.py
alurinium/image/image.py
alurinium/image/keystores.py
alurinium/image/models.py
alurinium/image/processor.py
alurinium/image/tasks.py
alurinium/image/filters/__init__.py
alurinium/image/filters/base.py
alurinium/image/filters/grayscale.py
alurinium/image/filters/resize.py
alurinium/image/templatetags/__init__.py
alurinium/image/templatetags/image_processing.py
alurinium_image_processing.egg-info/PKG-INFO
alurinium_image_processing.egg-info/SOURCES.txt
alurinium_image_processing.egg-info/dependency_links.txt
alurinium_image_processing.egg-info/requires.txt
alurinium_image_processing.egg-info/top_level.txt