Metadata-Version: 1.0
Name: alurinium-image-processing
Version: 0.1.2-dev
Summary: Useful image processing utils using Pillow
Home-page: http://pypi.python.org/pypi/alurinium-image-processing/
Author: Vasiliy Sheredeko
Author-email: piphon@gmail.com
License: LICENSE.txt
Platform: UNKNOWN
